Metadata-Version: 2.1
Name: odoo-addon-hr_employee_phone_extension
Version: 18.0.1.0.0.2
Requires-Python: >=3.10
Requires-Dist: odoo==18.0.*
Summary: Employee Phone Extension
Home-page: https://github.com/OCA/hr
License: AGPL-3
Author: Savoir-faire Linux,Odoo Community Association (OCA)
Author-email: support@odoo-community.org
Classifier: Programming Language :: Python
Classifier: Framework :: Odoo
Classifier: Framework :: Odoo :: 18.0
Classifier: License :: OSI Approved :: GNU Affero General Public License v3
